{

  "Boulder": [

    {
      "density": 2,
      "friction": 0,
      "bounce": 0,
      "filter": {
        "categoryBits": 1,
        "maskBits": 65535
      },
      "shape": [19, 4, 34, 10, 48, 17, 48, 25, 7, 28, 1, 19, 5, 5]
    },
    {
      "density": 2,
      "friction": 0,
      "bounce": 0,
      "filter": {
        "categoryBits": 1,
        "maskBits": 65535
      },
      "shape": [48, 59, 32, 53, 6, 39, 7, 28, 48, 25, 59, 33, 63, 47, 60, 57]
    },
    {
      "density": 2,
      "friction": 0,
      "bounce": 0,
      "filter": {
        "categoryBits": 1,
        "maskBits": 65535
      },
      "shape": [6, 39, 32, 53, 20, 59]
    },
    {
      "density": 2,
      "friction": 0,
      "bounce": 0,
      "filter": {
        "categoryBits": 1,
        "maskBits": 65535
      },
      "shape": [53, 8, 48, 17, 34, 10, 43, 0, 50, 2]
    }
  ],
  "Ship": [

    {
      "density": 2,
      "friction": 0,
      "bounce": 0,
      "filter": {
        "categoryBits": 1,
        "maskBits": 65535
      },
      "shape": [32, 45, 32, 0, 59, 62]
    },
    {
      "density": 2,
      "friction": 0,
      "bounce": 0,
      "filter": {
        "categoryBits": 1,
        "maskBits": 65535
      },
      "shape": [7, 62, 32, 0, 32, 45]
    }
  ],
  "Bullet": [

    {
      "density": 2,
      "friction": 0,
      "bounce": 0,
      "filter": {
        "categoryBits": 1,
        "maskBits": 65535
      },
      "shape": [8, 0, 8, 8, 0, 8, 0, 0]
    }
  ],
  "Boulder128": [

    {
      "density": 2,
      "friction": 0,
      "bounce": 0,
      "filter": {
        "categoryBits": 1,
        "maskBits": 65535
      },
      "shape": [117, 10, 120, 31, 120, 42, 97, 88, 88, 90, 74, 29, 84, 5]
    },
    {
      "density": 2,
      "friction": 0,
      "bounce": 0,
      "filter": {
        "categoryBits": 1,
        "maskBits": 65535
      },
      "shape": [38, 22, 7, 65, 3, 30, 14, 4, 35, 6]
    },
    {
      "density": 2,
      "friction": 0,
      "bounce": 0,
      "filter": {
        "categoryBits": 1,
        "maskBits": 65535
      },
      "shape": [63, 35, 88, 90, 19, 76, 7, 65, 38, 22]
    },
    {
      "density": 2,
      "friction": 0,
      "bounce": 0,
      "filter": {
        "categoryBits": 1,
        "maskBits": 65535
      },
      "shape": [97, 88, 120, 42, 125, 62, 122, 90, 112, 96]
    },
    {
      "density": 2,
      "friction": 0,
      "bounce": 0,
      "filter": {
        "categoryBits": 1,
        "maskBits": 65535
      },
      "shape": [55, 124, 26, 122, 5, 103, 19, 76, 88, 90, 78, 116]
    },
    {
      "density": 2,
      "friction": 0,
      "bounce": 0,
      "filter": {
        "categoryBits": 1,
        "maskBits": 65535
      },
      "shape": [5, 103, 26, 122, 10, 114]
    },
    {
      "density": 2,
      "friction": 0,
      "bounce": 0,
      "filter": {
        "categoryBits": 1,
        "maskBits": 65535
      },
      "shape": [120, 31, 117, 10, 121, 19]
    },
    {
      "density": 2,
      "friction": 0,
      "bounce": 0,
      "filter": {
        "categoryBits": 1,
        "maskBits": 65535
      },
      "shape": [74, 29, 88, 90, 63, 35]
    }
  ],
  "PaperBoulder2000": [{
    "shape": [588, 82, 693, 6, 695, 5]
  }, {
    "shape": [695, 5, 834, 59, 952, 138]
  }, {
    "shape": [952, 138, 1276, 50, 1358, 55]
  }, {
    "shape": [1358, 55, 1403, 79, 1522, 217]
  }, {
    "shape": [1522, 217, 1617, 352, 1572, 498]
  }, {
    "shape": [1583, 684, 1875, 806, 1962, 1052]
  }, {
    "shape": [1962, 1052, 1999, 1269, 1987, 1318]
  }, {
    "shape": [1987, 1318, 1915, 1397, 1813, 1494]
  }, {
    "shape": [1723, 1559, 1649, 1637, 1617, 1645]
  }, {
    "shape": [1617, 1645, 1561, 1615, 1545, 1595]
  }, {
    "shape": [1431, 1560, 1404, 1601, 1391, 1612]
  }, {
    "shape": [1312, 1670, 1211, 1793, 1019, 1868]
  }, {
    "shape": [1019, 1868, 856, 1976, 803, 1991]
  }, {
    "shape": [803, 1991, 744, 1976, 631, 1911]
  }, {
    "shape": [631, 1911, 424, 1897, 373, 1882]
  }, {
    "shape": [135, 1520, 49, 1479, 42, 1457]
  }, {
    "shape": [42, 1457, 29, 1451, 25, 1327]
  }, {
    "shape": [34, 1273, 14, 1205, 14, 1083]
  }, {
    "shape": [14, 1083, 2, 1036, 5, 1015]
  }, {
    "shape": [64, 920, 104, 785, 161, 663]
  }, {
    "shape": [314, 497, 319, 309, 469, 192]
  }, {
    "shape": [469, 192, 588, 82, 695, 5]
  }, {
    "shape": [952, 138, 1358, 55, 1522, 217]
  }, {
    "shape": [1522, 217, 1572, 498, 1583, 684]
  }, {
    "shape": [1583, 684, 1962, 1052, 1987, 1318]
  }, {
    "shape": [1987, 1318, 1813, 1494, 1723, 1559]
  }, {
    "shape": [1723, 1559, 1617, 1645, 1545, 1595]
  }, {
    "shape": [1431, 1560, 1391, 1612, 1379, 1607]
  }, {
    "shape": [1379, 1607, 1312, 1670, 1019, 1868]
  }, {
    "shape": [1019, 1868, 803, 1991, 631, 1911]
  }, {
    "shape": [631, 1911, 373, 1882, 328, 1677]
  }, {
    "shape": [234, 1587, 135, 1520, 42, 1457]
  }, {
    "shape": [42, 1457, 25, 1327, 34, 1273]
  }, {
    "shape": [14, 1083, 5, 1015, 64, 920]
  }, {
    "shape": [64, 920, 161, 663, 314, 497]
  }, {
    "shape": [314, 497, 469, 192, 695, 5]
  }, {
    "shape": [952, 138, 1522, 217, 1583, 684]
  }, {
    "shape": [1583, 684, 1987, 1318, 1723, 1559]
  }, {
    "shape": [1723, 1559, 1545, 1595, 1431, 1560]
  }, {
    "shape": [1431, 1560, 1379, 1607, 1019, 1868]
  }, {
    "shape": [1019, 1868, 631, 1911, 328, 1677]
  }, {
    "shape": [234, 1587, 42, 1457, 34, 1273]
  }, {
    "shape": [34, 1273, 14, 1083, 64, 920]
  }, {
    "shape": [64, 920, 314, 497, 695, 5]
  }, {
    "shape": [695, 5, 952, 138, 1583, 684]
  }, {
    "shape": [1583, 684, 1723, 1559, 1431, 1560]
  }, {
    "shape": [1431, 1560, 1019, 1868, 328, 1677]
  }, {
    "shape": [312, 1656, 234, 1587, 34, 1273]
  }, {
    "shape": [34, 1273, 64, 920, 695, 5]
  }, {
    "shape": [695, 5, 1583, 684, 1431, 1560]
  }, {
    "shape": [1431, 1560, 328, 1677, 312, 1656]
  }, {
    "shape": [312, 1656, 34, 1273, 695, 5]
  }, {
    "shape": [695, 5, 1431, 1560, 312, 1656]
  }],
  "PaperBoulder300": [{
    "shape": [101, 3, 102, 1, 121, 7]
  }, {
    "shape": [142, 21, 189, 8, 210, 12]
  }, {
    "shape": [210, 12, 242, 54, 235, 72]
  }, {
    "shape": [237, 102, 279, 120, 295, 164]
  }, {
    "shape": [295, 164, 299, 192, 246, 245]
  }, {
    "shape": [213, 234, 181, 267, 120, 298]
  }, {
    "shape": [96, 286, 58, 282, 48, 249]
  }, {
    "shape": [48, 249, 4, 214, 1, 152]
  }, {
    "shape": [1, 152, 25, 98, 48, 73]
  }, {
    "shape": [48, 73, 48, 47, 101, 3]
  }, {
    "shape": [101, 3, 121, 7, 142, 21]
  }, {
    "shape": [142, 21, 210, 12, 235, 72]
  }, {
    "shape": [237, 102, 295, 164, 246, 245]
  }, {
    "shape": [213, 234, 120, 298, 96, 286]
  }, {
    "shape": [96, 286, 48, 249, 1, 152]
  }, {
    "shape": [1, 152, 48, 73, 101, 3]
  }, {
    "shape": [101, 3, 142, 21, 235, 72]
  }, {
    "shape": [235, 72, 237, 102, 246, 245]
  }, {
    "shape": [213, 234, 96, 286, 1, 152]
  }, {
    "shape": [1, 152, 101, 3, 235, 72]
  }, {
    "shape": [235, 72, 246, 245, 213, 234]
  }, {
    "shape": [213, 234, 1, 152, 235, 72]
  }],
  "Ship1": [{
      "shape": [23, 12, 29, 1, 31, 0]
    },
    {
      "shape": [31, 0, 42, 2, 47, 11]
    },
    {
      "shape": [51, 49, 57, 52, 59, 62]
    },
    {
      "shape": [59, 62, 70, 65, 68, 80]
    },
    {
      "shape": [68, 80, 51, 83, 44, 77]
    },
    {
      "shape": [27, 77, 15, 83, 0, 77]
    },
    {
      "shape": [0, 77, 0, 65, 10, 62]
    },
    {
      "shape": [10, 62, 14, 49, 19, 47]
    },
    {
      "shape": [19, 47, 23, 12, 31, 0]
    },
    {
      "shape": [31, 0, 47, 11, 51, 49]
    },
    {
      "shape": [51, 49, 59, 62, 68, 80]
    },
    {
      "shape": [27, 77, 0, 77, 10, 62]
    },
    {
      "shape": [19, 47, 31, 0, 51, 49]
    },
    {
      "shape": [51, 49, 68, 80, 44, 77]
    },
    {
      "shape": [44, 77, 27, 77, 10, 62]
    },
    {
      "shape": [10, 62, 19, 47, 51, 49]
    },
    {
      "shape": [51, 49, 44, 77, 10, 62]
    }
  ],
  "Ship2": [{
      "shape": [42, 2, 43, 0, 87, 0]
    },
    {
      "shape": [87, 0, 112, 6, 114, 12]
    },
    {
      "shape": [114, 80, 120, 111, 114, 139]
    },
    {
      "shape": [114, 139, 117, 169, 106, 176]
    },
    {
      "shape": [122, 186, 127, 165, 142, 167]
    },
    {
      "shape": [142, 167, 148, 180, 148, 200]
    },
    {
      "shape": [148, 200, 135, 221, 129, 205]
    },
    {
      "shape": [129, 205, 123, 221, 114, 225]
    },
    {
      "shape": [114, 225, 112, 236, 93, 235]
    },
    {
      "shape": [48, 218, 40, 235, 21, 235]
    },
    {
      "shape": [19, 224, 12, 222, 0, 200]
    },
    {
      "shape": [0, 200, 4, 167, 6, 164]
    },
    {
      "shape": [11, 172, 13, 159, 20, 153]
    },
    {
      "shape": [20, 153, 14, 113, 19, 81]
    },
    {
      "shape": [19, 81, 19, 13, 21, 7]
    },
    {
      "shape": [21, 7, 42, 2, 87, 0]
    },
    {
      "shape": [87, 0, 114, 12, 114, 80]
    },
    {
      "shape": [114, 80, 114, 139, 106, 176]
    },
    {
      "shape": [122, 186, 142, 167, 148, 200]
    },
    {
      "shape": [129, 205, 114, 225, 93, 235]
    },
    {
      "shape": [48, 218, 21, 235, 19, 224]
    },
    {
      "shape": [0, 200, 6, 164, 7, 173]
    },
    {
      "shape": [20, 153, 19, 81, 21, 7]
    },
    {
      "shape": [21, 7, 87, 0, 114, 80]
    },
    {
      "shape": [113, 194, 122, 186, 148, 200]
    },
    {
      "shape": [129, 205, 93, 235, 89, 219]
    },
    {
      "shape": [48, 218, 19, 224, 0, 200]
    },
    {
      "shape": [0, 200, 7, 173, 11, 172]
    },
    {
      "shape": [20, 153, 21, 7, 114, 80]
    },
    {
      "shape": [113, 194, 148, 200, 129, 205]
    },
    {
      "shape": [129, 205, 89, 219, 63, 217]
    },
    {
      "shape": [63, 217, 48, 218, 0, 200]
    },
    {
      "shape": [0, 200, 11, 172, 20, 153]
    },
    {
      "shape": [20, 153, 114, 80, 106, 176]
    },
    {
      "shape": [113, 194, 129, 205, 63, 217]
    },
    {
      "shape": [63, 217, 0, 200, 20, 153]
    },
    {
      "shape": [20, 153, 106, 176, 113, 194]
    },
    {
      "shape": [113, 194, 63, 217, 20, 153]
    }
  ]
}